py_exec_cmd/__init__.py
py_exec_cmd/exec_cmd.py
py_exec_cmd-0.0.3.dist-info/LICENSE
py_exec_cmd-0.0.3.dist-info/METADATA
py_exec_cmd-0.0.3.dist-info/WHEEL
py_exec_cmd-0.0.3.dist-info/top_level.txt
py_exec_cmd-0.0.3.dist-info/RECORD
