Metadata-Version: 2.1
Name: py_exec_cmd
Version: 0.0.3
Summary: A wrapper for calling commands
Home-page: https://github.com/Serhii5465/py_exec_cmd
Author: Serhii5465
License: MIT
Classifier: Development Status :: 4 - Beta
Classifier: Environment :: Win32 (MS Windows)
Classifier: License :: OSI Approved :: MIT License
Classifier: Programming Language :: Python :: 3
Classifier: Operating System :: Microsoft :: Windows
Requires-Python: >=3.8
License-File: LICENSE
